{"paths":{"0":["i18n/sprite/hi/img_paytable_01",5],"1":["Sound/bgm_hall",2],"2":["i18n/sprite/en/img_paytable_01",5],"3":["Texture/Menu/img_switch_on",5],"4":["i18n/sprite/en/img_paytable_02",5],"5":["Texture/Menu/img_switch_off",5],"6":["i18n/sprite/hi/img_paytable_02",5],"7":["Texture/Game/img_disable",5],"8":["Texture/Game/img_heart",4,1],"9":["Texture/Common/logo",4,1],"11":["Texture/Game/img_spades",4,1],"12":["Texture/Common/AutoAtlas",3],"15":["Scenes/Game/menu_layer",1],"16":["i18n/sprite/en/AutoAtlas",3],"17":["Texture/Game/AutoAtlas",3],"19":["Texture/Common/singleColor",4,1],"20":["Texture/Game/btn_base",4,1],"21":["i18n/sprite/hi/AutoAtlas",3],"22":["Texture/Menu/img_switch_off",4,1],"23":["i18n/sprite/hi/img_paytable_02",4,1],"24":["i18n/sprite/hi/img_paytable_01",4,1],"26":["i18n/label/en",0],"27":["Scenes/Game/low_balance_layer",1],"28":["i18n/sprite/en/img_paytable_02",4,1],"30":["Texture/Game/img_betChip",4,1],"31":["i18n/label/hi",0],"32":["Scenes/Game/help_layer",1],"33":["Texture/Game/img_club",4,1],"34":["Scenes/Game/chipSetting_layer",1],"35":["Config/app_info",0],"36":["Scenes/Game/betChip",1],"37":["Texture/Game/img_play",4,1],"38":["Scenes/Game/award_layer",1],"39":["Texture/Game/Paytable/AutoAtlas",3],"40":["Texture/Menu/img_switch_on",4,1],"42":["Config/url_config",0],"43":["Texture/Game/img_disable",4,1],"44":["Scenes/Game/btn_bet",1],"45":["Texture/Game/img_diamond",4,1],"46":["Texture/Game/img_game_logo",4,1],"47":["Texture/Game/img_crown",4,1],"49":["Texture/Game/img_flag",4,1],"51":["i18n/sprite/en/img_paytable_01",4,1],"52":["Scenes/Game/language_layer",1],"53":["Scenes/Game/paytable_layer",1]},"types":["cc.JsonAsset","cc.Prefab","cc.AudioClip","cc.SpriteAtlas","cc.SpriteFrame","cc.Texture2D"],"uuids":["1c963gr/lJkpX7Io09eQUu","32OlH7+uxCU7kgUiGoz681","4arcYUdEtCqpmTv/2+Ypr0","68MU9zb0VCdpmbatR4bnZ4","81qStFbLhIca5llXahWxO+","84mEH/voVOy5OYRIRUN1fa","9aZ36OOFJIkaMFN5Q9GfQX","aeB43FOJtCHpM+5VbxUjs1","06OWTJJgJFy4VhF2oKY9mK","12nt5x1cFMnbfD4hQSXSSh","16Imc8bMFBELQ2mXPRpmcW","16hFoS1WRI1bJOrTnnfWyf","16lnULmvVGd5N0xzVjrwqi","1768f0a38","19fa97075","26HxcufDpDY7Ut1nGmscFz","27culxxJpDbLvIllJfufmY","37N9VNtCNPi7AWGmDvFyWI","3ax89ffylApLlkF0/a4eQc","41D7kWhyFGY7q4NDlzkazn","437Rl0yBVJSq1d/we36rzE","46G1exzt5C+bllm/TwXu1F","46fFJ0E9RPH497Xzc7CWkr","551lgUyA9LAKgfirVFW5PR","58Do5zP/JCxpVczZ2v9tX+","5cnx1lWTlHQa7VRvcbzLZH","60OXjFjUFGKJc2tY10uXpw","62s2d1DUpDzo0TPxBrIUZy","68vMfXkKJKcLFoKYw/tHJg","71VhFCTINJM6/Ky3oX9nBT","73SW7ytOJDfosU8zJ3TB/A","84W/cAz85HoYn7nHwgIBAc","85hSKy9FpFUowXhYQq39My","85r38uvJ1ImoXaS1CEnIk1","8b/oyCB6pLSaNZ/mnrfXo1","932NCumZJI+6mSwJ/6Fcly","99ododJwVJeptwDABIvnyS","9fFGzkeA9M1J0jARmFF3AR","a6waA4jOVP97XnkPSpFdL3","aaVmKKvbVFWK7cWe9g/nOI","adH02YR8pOpKXAjBSZ3JnP","b4P/PCArtIdIH38t6mlw8Y","b81Gv7kpJBZp8aqjNtY2lM","b9xM26VABDkKuLSqpoCvtT","bc6DntwKhHpbBcdcYhJN9h","beVDmSDcBO+YOdIxEMx+HK","d1lacOQ8FDO5HgXzXXbkXB","d6pOKN53hBZr8EcUAodxHR","d608qFRoFHwbXd0Dap056i","e2/ztkLb1CbajHdmfgObiu","e8Ueib+qJEhL6mXAHdnwbi","e89ljwVClNlrHykJZTceq7","eda+JcCLtBaqRx6xz3L7tk","ef80MpUg1BPLZmo8wZGOtt","29FYIk+N1GYaeWH/q1NxQO","5cO7kybDxGj4ipyMYdRYZB","e97GVMl6JHh5Ml5qEDdSGa","ecpdLyjvZBwrvm+cedCcQy","f0BIwQ8D5Ml7nTNQbh1YlS"],"scenes":{"db://assets/resources/Scenes/Loading.fire":25,"db://assets/resources/Scenes/Lobby.fire":10,"db://assets/resources/Scenes/Game/Game.fire":18},"redirect":[57,0],"deps":["internal"],"packs":{"016990f7b":[8,11,18,33,37,43,45,46,47,49],"06284d0e3":[25,35,42],"0750126a3":[9,10],"0c339d10f":[54,56,58],"0cc4011b1":[15,22,40],"0de151a95":[13,14,0,2,3,29,4,5,6,7,41,48,50],"0e94086b2":[55,28,51]},"name":"resources","importBase":"import","nativeBase":"native","debug":false,"isZip":false,"encrypted":false,"versions":{"import":["016990f7b","058da","06284d0e3","ca77c","0750126a3","b56d2","0c339d10f","a9ccb","0cc4011b1","7dafe","0de151a95","c0b26","0e94086b2","45ea3",12,"5e6c6",16,"047d8",1,"be7aa",17,"7c5ed",19,"112cb",20,"1a5eb",21,"047d8",23,"7a21f",24,"42969",26,"8405c",27,"78b93",30,"b8331",31,"56e9d",32,"a044d",34,"6465c",36,"e10a6",38,"8cfff",39,"047d8",44,"0429f",52,"c922f",53,"07c76"],"native":[13,"07cfc",14,"141ad",0,"61e88",1,"e5afc",2,"81c97",3,"14ae1",29,"c06a9",4,"a7d13",5,"28012",6,"615eb",7,"ce838",41,"83fcc",48,"d55c2",50,"90cf4"]}}